bskytui/__init__.py
bskytui/app.py
bskytui/bskytui.tcss
bskytui/config/__init__.py
bskytui/config/settings.py
bskytui/services/__init__.py
bskytui/services/bsky.py
bskytui/utils/__init__.py
bskytui/utils/formatters.py
bskytui/widgets/__init__.py
bskytui/widgets/post.py
bskytui/widgets/stats.py
bskytui-0.0.1a0.dist-info/METADATA
bskytui-0.0.1a0.dist-info/WHEEL
bskytui-0.0.1a0.dist-info/entry_points.txt
bskytui-0.0.1a0.dist-info/RECORD
