Metadata-Version: 2.3
Name: bskytui
Version: 0.0.1a0
Requires-Python: >=3.12
Requires-Dist: atproto
Requires-Dist: pydantic-settings
Requires-Dist: textual
